ScaleConvertion/SC.py
ScaleConvertion/__init__.py
ScaleConvertion/Model/Efficientnet.py
ScaleConvertion/Model/Restnet.py
ScaleConvertion/Model/SwimModel.py
ScaleConvertion/Model/SwimModel_2.py
ScaleConvertion/Model/__init__.py
ScaleConvertion/Model/restnet_transformer.py
ScaleConvertion/PicProcess/ConcatAnswer.py
ScaleConvertion/PicProcess/DataPredict.py
ScaleConvertion/PicProcess/Draw_Window.py
ScaleConvertion/PicProcess/MakeData.py
ScaleConvertion/PicProcess/__init__.py
ScaleConvertion/PicProcess/save4_0.003732832917032445mt.pth
ScaleConvertion/Utiles/Info.py
ScaleConvertion/Utiles/PictureInfo.py
ScaleConvertion/Utiles/SED.py
ScaleConvertion/Utiles/SaveFile.py
ScaleConvertion/Utiles/ScaleCompute.py
ScaleConvertion/Utiles/__init__.py
ScaleConvertion/test/__init__.py
ScaleConvertion/test/test.py
ScaleConvertion/test/testuav.py
ScaleConvertion-0.6.dist-info/LICENSE
ScaleConvertion-0.6.dist-info/METADATA
ScaleConvertion-0.6.dist-info/WHEEL
ScaleConvertion-0.6.dist-info/top_level.txt
ScaleConvertion-0.6.dist-info/RECORD
