Metadata-Version: 2.1
Name: ScaleConvertion
Version: 0.6
Summary: Helps achieve surface reflectance scale conversion
Home-page: https://github.com/qxcnwu
Author: qxcnwu
Author-email: qxcnwu@gmail.com
Maintainer: qxcnwu
Maintainer-email: qxcnwu@gmail.com
License: MIT License
Classifier: Development Status :: 3 - Alpha
Classifier: Intended Audience :: Developers
Classifier: Topic :: Software Development :: Build Tools
Classifier: License :: OSI Approved :: MIT License
Classifier: Programming Language :: Python :: 3
Requires-Python: >=3.4
License-File: LICENSE
Requires-Dist: tqdm
Requires-Dist: numpy
Requires-Dist: pandas
Requires-Dist: torch
Requires-Dist: timm
Requires-Dist: exifread
Requires-Dist: qt5-applications
Requires-Dist: matplotlib
Requires-Dist: torchvision
Requires-Dist: requests
Requires-Dist: colour
Requires-Dist: opencv-python
Requires-Dist: gdal
